setup.py
bike_geo/Bike.py
bike_geo/__init__.py
bike_geo.egg-info/PKG-INFO
bike_geo.egg-info/SOURCES.txt
bike_geo.egg-info/dependency_links.txt
bike_geo.egg-info/top_level.txt
bike_geo.egg-info/zip-safe