Metadata-Version: 1.0
Name: bike-geo
Version: 0.4
Summary: Calculates actual stack and reach, and other bike geometry
Home-page: UNKNOWN
Author: Matt Bray
Author-email: blazetolliver@icloud.com
License: UNKNOWN
Platform: UNKNOWN
